{
  "generated_at": "2026-07-09T18:45:01.969Z",
  "window_hours": 24,
  "items": [
    {
      "path": "/nights/busanmulnight",
      "title": "부산물나이트",
      "category": "night",
      "region": "부산",
      "views_24h": 6
    },
    {
      "path": "/yojeong/ilsan/ilsanmyeongwolgwanyojeong",
      "title": "일산명월관요정",
      "category": "yojeong",
      "region": "일산",
      "views_24h": 6
    },
    {
      "path": "/rooms/ilsan/ilsanroom",
      "title": "일산룸",
      "category": "room",
      "region": "일산",
      "views_24h": 5
    },
    {
      "path": "/nights/daejeonbongmyeongnight",
      "title": "대전봉명나이트",
      "category": "night",
      "region": "대전",
      "views_24h": 4
    },
    {
      "path": "/nights/gangseo-hobak",
      "title": "강서호박나이트",
      "category": "night",
      "region": "강서",
      "views_24h": 3
    },
    {
      "path": "/lounges/apgujeonglounge-dm",
      "title": "압구정라운지 디엠",
      "category": "lounge",
      "region": "압구정",
      "views_24h": 2
    },
    {
      "path": "/nights/daejeononenight",
      "title": "대전원나이트",
      "category": "night",
      "region": "대전",
      "views_24h": 2
    },
    {
      "path": "/nights/daejeonsevennight",
      "title": "대전세븐나이트",
      "category": "night",
      "region": "대전",
      "views_24h": 2
    },
    {
      "path": "/lounges/apgujeongidiotlounge",
      "title": "압구정이디엇라운지",
      "category": "lounge",
      "region": "압구정",
      "views_24h": 2
    },
    {
      "path": "/clubs/cheongju/cheongju-supermoon",
      "title": "청주클럽 슈퍼문",
      "category": "club",
      "region": "청주",
      "views_24h": 1
    },
    {
      "path": "/lounges/apgujeongcodelounge",
      "title": "압구정코드라운지",
      "category": "lounge",
      "region": "압구정",
      "views_24h": 1
    },
    {
      "path": "/nights/bucheongoraenight",
      "title": "부천고래나이트",
      "category": "night",
      "region": "부천",
      "views_24h": 1
    },
    {
      "path": "/nights/cheongjuhobaknight",
      "title": "청주호박나이트",
      "category": "night",
      "region": "청주",
      "views_24h": 1
    },
    {
      "path": "/nights/gurihobaknight",
      "title": "구리호박나이트",
      "category": "night",
      "region": "구리",
      "views_24h": 1
    },
    {
      "path": "/nights/ulsanchampionnight",
      "title": "울산챔피언나이트",
      "category": "night",
      "region": "울산",
      "views_24h": 1
    }
  ]
}